lichungtsaiTest/__init__.py
lichungtsaiTest/utils.py
lichungtsaiTest-0.1.1.dist-info/LICENSE
lichungtsaiTest-0.1.1.dist-info/METADATA
lichungtsaiTest-0.1.1.dist-info/WHEEL
lichungtsaiTest-0.1.1.dist-info/top_level.txt
lichungtsaiTest-0.1.1.dist-info/RECORD
