Metadata-Version: 2.1
Name: lichungtsaiTest
Version: 0.1.1
Summary: A simple test library for demonstration
Home-page: https://github.com/lichungtsai611/lichungtsaiTest
Author: Li-Chung Tsai
Author-email: lichungtsai611@gmail.com
License: MIT
License-File: LICENSE
